poeblix/__init__.py
poeblix/plugins.py
poeblix/util/__init__.py
poeblix/util/util.py
poeblix/validatedocker.py
poeblix/validatewheel.py
poeblix-0.10.dist-info/entry_points.txt
poeblix-0.10.dist-info/LICENSE
poeblix-0.10.dist-info/METADATA
poeblix-0.10.dist-info/WHEEL
poeblix-0.10.dist-info/RECORD
