Metadata-Version: 2.1
Name: poeblix
Version: 0.10
Summary: Poetry plugin that adds support for building wheel files using the poetry.lock file, and data_files just like in setup.py
Home-page: https://github.com/spoorn/poeblix
Keywords: poeblix,utility,poetry,plugin,poetry-plugin,wheel,distribution,data_files
Author: spoorn
Author-email: spookump@gmail.com
Requires-Python: >=3.9,<4.0
Classifier: Programming Language :: Python
Classifier: Programming Language :: Python :: 3
Classifier: Programming Language :: Python :: 3.9
Classifier: Programming Language :: Python :: 3.10
Classifier: Programming Language :: Python :: 3.11
Classifier: Topic :: Software Development :: Code Generators
Classifier: Topic :: Software Development :: Libraries
Classifier: Topic :: Software Development :: Libraries :: Python Modules
Requires-Dist: poetry (>=1.2.0rc1,<2.0)
Project-URL: Repository, https://github.com/spoorn/poeblix
